{"nodes": [{"id": "app_components_product_productdescription_tsx", "label": "ProductDescription.tsx", "file_type": "code", "source_file": "app\\components\\Product\\ProductDescription.tsx", "source_location": "L1"}, {"id": "productdescription_check", "label": "check()", "file_type": "code", "source_file": "app\\components\\Product\\ProductDescription.tsx", "source_location": "L11"}], "edges": [{"source": "app_components_product_productdescription_tsx", "target": "react", "relation": "imports_from", "confidence": "EXTRACTED", "source_file": "app\\components\\Product\\ProductDescription.tsx", "source_location": "L1", "weight": 1.0}, {"source": "app_components_product_productdescription_tsx", "target": "productdescription_check", "relation": "contains", "confidence": "EXTRACTED", "source_file": "app\\components\\Product\\ProductDescription.tsx", "source_location": "L11", "weight": 1.0}], "unresolved_calls": [{"source": "productdescription_check", "label": "parseFloat", "line": 12}, {"source": "productdescription_check", "label": "getComputedStyle", "line": 12}, {"source": "productdescription_check", "label": "setOverflows", "line": 13}]}